pyglui/custom.pxi
pyglui/design_params.pxi
pyglui/gldraw.pxi
pyglui/graph.cp36-win_amd64.pyd
pyglui/graph.cpp
pyglui/graph.pyx
pyglui/helpers.pxi
pyglui/menus.pxi
pyglui/OpenSans-Regular.ttf
pyglui/pupil_icons.ttf
pyglui/Roboto-Regular.ttf
pyglui/timelines.pxi
pyglui/ui.cp36-win_amd64.pyd
pyglui/ui.cpp
pyglui/ui.pyx
pyglui/ui_elements.pxi
pyglui/__init__.py
pyglui/cygl/glew.pxd
pyglui/cygl/include_glew.h
pyglui/cygl/LICENSE
pyglui/cygl/README.md
pyglui/cygl/shader.cp36-win_amd64.pyd
pyglui/cygl/shader.cpp
pyglui/cygl/shader.pxd
pyglui/cygl/shader.pyx
pyglui/cygl/unhandled_glew.h
pyglui/cygl/utils.cp36-win_amd64.pyd
pyglui/cygl/utils.cpp
pyglui/cygl/utils.pxd
pyglui/cygl/utils.pyx
pyglui/cygl/__init__.py
pyglui/cygl/win_glew/glew32.dll
pyglui/cygl/win_glew/glew32.lib
pyglui/cygl/win_glew/glew32s.lib
pyglui/cygl/win_glew/GL/glew.h
pyglui/pyfontstash/cfontstash.pxd
pyglui/pyfontstash/fontstash.c
pyglui/pyfontstash/fontstash.cp36-win_amd64.pyd
pyglui/pyfontstash/fontstash.pxd
pyglui/pyfontstash/fontstash.pyx
pyglui/pyfontstash/LICENSE
pyglui/pyfontstash/README.md
pyglui/pyfontstash/setup.py
pyglui/pyfontstash/__init__.pxd
pyglui/pyfontstash/__init__.py
pyglui/pyfontstash/fontstash/example/error.c
pyglui/pyfontstash/fontstash/example/example.c
pyglui/pyfontstash/fontstash/src/fontstash.h
pyglui/pyfontstash/fontstash/src/gl3corefontstash.h
pyglui/pyfontstash/fontstash/src/glfontstash.h
pyglui/pyfontstash/fontstash/src/stb_truetype.h
pyglui-1.31.1.dist-info/DELVEWHEEL
pyglui-1.31.1.dist-info/LICENSE
pyglui-1.31.1.dist-info/METADATA
pyglui-1.31.1.dist-info/RECORD
pyglui-1.31.1.dist-info/top_level.txt
pyglui-1.31.1.dist-info/WHEEL
pyglui.libs/.load-order-pyglui-1.31.1
pyglui.libs/glew32-baaebca5d88ba831cd3597e4727aa07b.dll
pyglui.libs/msvcp140.dll
pyglui.libs/vcruntime140_1.dll
