Metadata-Version: 2.1
Name: pyglui
Version: 1.31.1
Summary: OpenGL UI powered by Cython
Home-page: https://github.com/pupil-labs/pyglui
Author: Pupil Labs GmbH
Author-email: pypi@pupil-labs.com
License: MIT
Project-URL: Changelog, https://github.com/pupil-labs/pyglui/blob/master/CHANGELOG.md
Platform: UNKNOWN
Classifier: Development Status :: 5 - Production/Stable
Classifier: Intended Audience :: Developers
Classifier: License :: OSI Approved :: GNU Lesser General Public License v3 (LGPLv3)
Classifier: License :: OSI Approved :: MIT License
Classifier: Natural Language :: English
Classifier: Programming Language :: Python :: 3
Classifier: Programming Language :: Python :: 3 :: Only
Classifier: Programming Language :: Python :: Implementation :: CPython
Requires-Python: >=3.6
License-File: LICENSE
Requires-Dist: numpy
Requires-Dist: cysignals ; platform_system != "Windows"
Provides-Extra: deploy
Requires-Dist: build ; extra == 'deploy'
Requires-Dist: bump2version ; extra == 'deploy'
Provides-Extra: dev
Requires-Dist: pre-commit ; extra == 'dev'
Requires-Dist: tox ; extra == 'dev'
Provides-Extra: examples
Requires-Dist: glfw ; extra == 'examples'
Requires-Dist: numpy ; extra == 'examples'
Requires-Dist: psutil ; extra == 'examples'
Requires-Dist: pyopengl ; extra == 'examples'
Provides-Extra: test
Requires-Dist: glfw ; extra == 'test'
